{
    "Hummingbird": {
        "checkpoints": [
            {
                "steps": 52883,
                "file_path": "results\\2DTorusVisual.3strafeinTorus\\Hummingbird\\Hummingbird-52883.onnx",
                "reward": 132.02441215515137,
                "creation_time": 1623154653.049167,
                "auxillary_file_paths": [
                    "results\\2DTorusVisual.3strafeinTorus\\Hummingbird\\Hummingbird-52883.pt"
                ]
            }
        ],
        "final_checkpoint": {
            "steps": 52883,
            "file_path": "results\\2DTorusVisual.3strafeinTorus\\Hummingbird.onnx",
            "reward": 132.02441215515137,
            "creation_time": 1623154653.049167,
            "auxillary_file_paths": [
                "results\\2DTorusVisual.3strafeinTorus\\Hummingbird\\Hummingbird-52883.pt"
            ]
        }
    },
    "metadata": {
        "stats_format_version": "0.3.0",
        "mlagents_version": "0.26.0",
        "torch_version": "1.7.1+cu110"
    }
}